odoo/addons/storage_image_backend_migration/README.rst
odoo/addons/storage_image_backend_migration/__init__.py
odoo/addons/storage_image_backend_migration/__manifest__.py
odoo/addons/storage_image_backend_migration/data/queue_job_channel_data.xml
odoo/addons/storage_image_backend_migration/data/queue_job_function_data.xml
odoo/addons/storage_image_backend_migration/i18n/storage_image_backend_migration.pot
odoo/addons/storage_image_backend_migration/readme/CONTRIBUTORS.rst
odoo/addons/storage_image_backend_migration/readme/DESCRIPTION.rst
odoo/addons/storage_image_backend_migration/readme/USAGE.rst
odoo/addons/storage_image_backend_migration/security/ir.model.access.csv
odoo/addons/storage_image_backend_migration/static/description/icon.png
odoo/addons/storage_image_backend_migration/static/description/index.html
odoo/addons/storage_image_backend_migration/views/storage_image_backend_migration_wizard_views.xml
odoo/addons/storage_image_backend_migration/wizards/__init__.py
odoo/addons/storage_image_backend_migration/wizards/storage_image_backend_migration_wizard.py
odoo_addon_storage_image_backend_migration-15.0.1.0.0.2.dist-info/METADATA
odoo_addon_storage_image_backend_migration-15.0.1.0.0.2.dist-info/WHEEL
odoo_addon_storage_image_backend_migration-15.0.1.0.0.2.dist-info/top_level.txt
odoo_addon_storage_image_backend_migration-15.0.1.0.0.2.dist-info/RECORD
