Metadata-Version: 2.1
Name: odoo-addon-storage-image-backend-migration
Version: 15.0.1.0.0.2
Summary: Migrate src backend to destination backend
Home-page: https://github.com/OCA/storage
Author: ForgeFlow, Odoo Community Association (OCA)
Author-email: support@odoo-community.org
License: AGPL-3
Platform: UNKNOWN
Classifier: Programming Language :: Python
Classifier: Framework :: Odoo
Classifier: Framework :: Odoo :: 15.0
Classifier: License :: OSI Approved :: GNU Affero General Public License v3
Classifier: Development Status :: 3 - Alpha
Requires-Python: >=3.8
Requires-Dist: odoo-addon-queue-job <15.1dev,>=15.0dev
Requires-Dist: odoo-addon-storage-file <15.1dev,>=15.0dev
Requires-Dist: odoo-addon-storage-image <15.1dev,>=15.0dev
Requires-Dist: odoo <15.1dev,>=15.0a
Requires-Dist: python-magic
Requires-Dist: validators
